LICENSE
MANIFEST.in
README.rst
setup.py
pytwitch/__init__.py
pytwitch/__project__.py
pytwitch/channels.py
pytwitch/streamtip.py
pytwitch/utils.py
pytwitch.egg-info/PKG-INFO
pytwitch.egg-info/SOURCES.txt
pytwitch.egg-info/dependency_links.txt
pytwitch.egg-info/not-zip-safe
pytwitch.egg-info/requires.txt
pytwitch.egg-info/top_level.txt