Metadata-Version: 1.1
Name: pytwitch
Version: 0.0.6
Summary: PyTwitch - Twitch Integration for Python
Home-page: https://github.com/dhh-hss/pytwitch
Author: Daniel Hyldebrandt Hemmingsen
Author-email: daniel.h.hemmingsen@gmail.com
License: MIT
Keywords: twitch,api,development
Platform: UNKNOWN
Classifier: Development Status :: 1 - Planning
Classifier: Intended Audience :: Developers
Classifier: Natural Language :: English
Classifier: License :: OSI Approved :: MIT License
Classifier: Programming Language :: Python
Classifier: Programming Language :: Python :: 3.2
Classifier: Programming Language :: Python :: 3.3
Classifier: Programming Language :: Python :: 3.4
Classifier: Topic :: Software Development :: Build Tools
